{
  "digits": "5853399800",
  "kind": "phone",
  "primaryName": "entry-callout:rochester-housing-authority-waitlist-ny",
  "rawValue": "(585) 339-9800",
  "blockDial": false,
  "tags": [
    "entry-callout"
  ],
  "sourceOwners": [
    {
      "type": "entry",
      "id": "rochester-housing-authority-waitlist-ny",
      "line": 26
    }
  ],
  "callsRecorded": 1,
  "mostRecent": {
    "run": "2026-05-03T06-41-32-330Z_1c38454b-fdf6-c67a-32da-40c8054a297d",
    "meta": {
      "callId": "1c38454b-fdf6-c67a-32da-40c8054a297d",
      "digits": "5853399800",
      "dialedNumber": "(585) 339-9800",
      "catalogedName": "rochester-housing-authority-waitlist-ny",
      "sourceId": "legal-entry:rochester-housing-authority-waitlist-ny",
      "sourceOwners": [
        {
          "type": "entry",
          "id": "rochester-housing-authority-waitlist-ny"
        }
      ],
      "dialIntentTs": "2026-05-03T06:41:32.330Z",
      "durationSec": null,
      "status": "error",
      "reason": "phonelink-not-running",
      "endedReason": null,
      "artifacts": {
        "audio": null,
        "screenshot": null,
        "transcript": null,
        "verdict": "verdict.json"
      },
      "quality": "unknown",
      "migration": {
        "sourceFile": "call-data/results.json",
        "migratedAt": "2026-05-03T19:05:27.066Z"
      }
    },
    "verdict": {
      "bucket": "no-content",
      "confidence": 0.95,
      "reason": "empty or too-short transcript"
    }
  },
  "status": "active",
  "needsRedial": false,
  "replacedBy": null,
  "replaces": null,
  "seededAt": "2026-05-03T19:44:16.560Z",
  "lastSeededAt": "2026-05-03T19:44:16.560Z"
}