{
  "digits": "2124168400",
  "kind": "phone",
  "primaryName": "entry-callout:health-insurance-external-appeal-ny",
  "rawValue": "(212) 416-8400",
  "blockDial": false,
  "tags": [
    "entry-callout"
  ],
  "sourceOwners": [
    {
      "type": "entry",
      "id": "health-insurance-external-appeal-ny",
      "line": 46
    },
    {
      "type": "entry",
      "id": "long-term-care-insurance-ny",
      "line": 48
    }
  ],
  "callsRecorded": 2,
  "mostRecent": {
    "run": "2026-05-03T08-56-43-108Z_9a6100ba-43cd-2cef-5aa2-0d1c4cdb497b",
    "meta": {
      "callId": "9a6100ba-43cd-2cef-5aa2-0d1c4cdb497b",
      "digits": "2124168400",
      "dialedNumber": "(212) 416-8400",
      "catalogedName": "health-insurance-external-appeal-ny",
      "sourceId": "legal-entry:health-insurance-external-appeal-ny",
      "sourceOwners": [
        {
          "type": "entry",
          "id": "health-insurance-external-appeal-ny"
        },
        {
          "type": "entry",
          "id": "long-term-care-insurance-ny"
        }
      ],
      "dialIntentTs": "2026-05-03T08:56:43.108Z",
      "durationSec": 26,
      "status": "success",
      "reason": null,
      "endedReason": "max-duration",
      "artifacts": {
        "audio": null,
        "screenshot": null,
        "transcript": "transcript.txt",
        "verdict": "verdict.json"
      },
      "quality": "trusted",
      "migration": {
        "sourceFile": "call-data/results.json",
        "migratedAt": "2026-05-03T19:05:27.731Z"
      }
    },
    "verdict": {
      "bucket": "drift-candidate",
      "confidence": 0.7,
      "score": 0,
      "extracted": "Attorney General's Charities Bureau",
      "reason": "transcript-stated name (Attorney General's Charities Bureau) differs from catalogued (health-insurance-external-appeal-ny)"
    }
  },
  "status": "active",
  "needsRedial": false,
  "replacedBy": null,
  "replaces": null,
  "seededAt": "2026-05-03T19:44:16.395Z",
  "lastSeededAt": "2026-05-03T19:44:16.395Z"
}